myogen/__init__.py
myogen/config/alpha_mn_default.yaml
myogen/simulator/__init__.py
myogen/simulator/core/__init__.py
myogen/simulator/core/physiological_distribution.py
myogen/simulator/core/emg/__init__.py
myogen/simulator/core/emg/electrodes.py
myogen/simulator/core/emg/intramuscular/__init__.py
myogen/simulator/core/emg/intramuscular/bioelectric.py
myogen/simulator/core/emg/intramuscular/intramuscular_emg.py
myogen/simulator/core/emg/intramuscular/motor_unit_sim.py
myogen/simulator/core/emg/surface/__init__.py
myogen/simulator/core/emg/surface/simulate_fiber.py
myogen/simulator/core/emg/surface/surface_emg.py
myogen/simulator/core/force/__init__.py
myogen/simulator/core/force/biomechanics.py
myogen/simulator/core/force/force_model.py
myogen/simulator/core/force/force_model_vectorized.py
myogen/simulator/core/force/force_utils.py
myogen/simulator/core/force/force_utils_vectorized.py
myogen/simulator/core/muscle/__init__.py
myogen/simulator/core/muscle/muscle.py
myogen/simulator/core/muscle/voronoi_pi1e5.csv
myogen/simulator/neuron/__init__.py
myogen/simulator/neuron/cells.py
myogen/simulator/neuron/joint_dynamics.py
myogen/simulator/neuron/muscle.py
myogen/simulator/neuron/network.py
myogen/simulator/neuron/simulation_runner.py
myogen/simulator/neuron/_cython/_gamma_process_generator.c
myogen/simulator/neuron/_cython/_gamma_process_generator.cpython-312-x86_64-linux-gnu.so
myogen/simulator/neuron/_cython/_gamma_process_generator.pyx
myogen/simulator/neuron/_cython/_gto.c
myogen/simulator/neuron/_cython/_gto.cpython-312-x86_64-linux-gnu.so
myogen/simulator/neuron/_cython/_gto.pyx
myogen/simulator/neuron/_cython/_hill.c
myogen/simulator/neuron/_cython/_hill.cpython-312-x86_64-linux-gnu.so
myogen/simulator/neuron/_cython/_hill.pyx
myogen/simulator/neuron/_cython/_poisson_process_generator.c
myogen/simulator/neuron/_cython/_poisson_process_generator.cpython-312-x86_64-linux-gnu.so
myogen/simulator/neuron/_cython/_poisson_process_generator.pyx
myogen-0.8.5.dist-info/licenses/LICENSE.md
myogen-0.8.5.dist-info/METADATA
myogen-0.8.5.dist-info/WHEEL
myogen-0.8.5.dist-info/top_level.txt
myogen-0.8.5.dist-info/RECORD
