Metadata-Version: 2.4
Name: MyoGen
Version: 0.8.5
Summary: Modular and extensible neuromuscular simulation framework for generating physiologically grounded motor-unit activity, muscle force, and EMG signals (surface and intramuscular)
Author-email: "Raul C. Sîmpetru" <raul.simpetru@fau.de>, Renato Naville Watanabe <renato.navillewatanabe@gmail.com>
Maintainer-email: "Raul C. Sîmpetru" <raul.simpetru@fau.de>
License-Expression: AGPL-3.0-or-later
Project-URL: Homepage, https://nsquaredlab.github.io/MyoGen/
Project-URL: Documentation, https://nsquaredlab.github.io/MyoGen/
Project-URL: Repository, https://github.com/NsquaredLab/MyoGen
Project-URL: Issues, https://github.com/NsquaredLab/MyoGen/issues
Project-URL: Changelog, https://github.com/NsquaredLab/MyoGen/blob/main/CHANGELOG.md
Keywords: EMG,electromyography,neuromuscular,simulation,motor-unit,NEURON,neuroscience
Classifier: Development Status :: 4 - Beta
Classifier: Intended Audience :: Science/Research
Classifier: Operating System :: POSIX :: Linux
Classifier: Operating System :: MacOS
Classifier: Operating System :: Microsoft :: Windows
Classifier: Programming Language :: Python :: 3
Classifier: Programming Language :: Python :: 3.12
Classifier: Programming Language :: Python :: 3 :: Only
Classifier: Topic :: Scientific/Engineering
Classifier: Topic :: Scientific/Engineering :: Bio-Informatics
Classifier: Topic :: Scientific/Engineering :: Medical Science Apps.
Requires-Python: >=3.12
License-File: LICENSE.md
Requires-Dist: beartype>=0.21.0
Requires-Dist: cython>=3.1.3
Requires-Dist: elephant>=1.1.1
Requires-Dist: impi-rt>=2021.15.0; sys_platform == "win32"
Requires-Dist: matplotlib>=3.10.1
Requires-Dist: mpi4py>=4.0.3
Requires-Dist: neuron==8.2.7; sys_platform == "linux" or sys_platform == "darwin"
Requires-Dist: numba>=0.61.2
Requires-Dist: numpy<2.0,>=1.26
Requires-Dist: optuna>=4.5.0
Requires-Dist: quantities>=0.16.2
Requires-Dist: scienceplots>=2.1.1
Requires-Dist: scikit-fmm>=2025.1.29
Requires-Dist: scikit-learn>=1.6.1
Requires-Dist: scipy>=1.15.3
Requires-Dist: seaborn>=0.13.2
Requires-Dist: setuptools>=80.9.0
Requires-Dist: tqdm>=4.67.1
Requires-Dist: viziphant>=0.4.0
Provides-Extra: nwb
Requires-Dist: pynwb>=2.8.0; extra == "nwb"
Requires-Dist: nwbinspector>=0.5.0; extra == "nwb"
Dynamic: license-file
